wwpdb/utils/detach/DetachUtils.py
wwpdb/utils/detach/DetachedProcessBase.py
wwpdb/utils/detach/SubProcessUtil.py
wwpdb/utils/detach/__init__.py
wwpdb_utils_detach-0.5.0.dist-info/METADATA
wwpdb_utils_detach-0.5.0.dist-info/WHEEL
wwpdb_utils_detach-0.5.0.dist-info/RECORD
