Metadata-Version: 2.4
Name: wwpdb.utils.detach
Version: 0.5.0
Summary: WWPDB Python Detached Process Utilities
Project-URL: Homepage, https://github.com/rcsb/py-wwpdb_utils_detach
Author-email: Ezra Peisach <ezra.peisach@rcsb.org>
License-Expression: Apache-2.0
Classifier: Development Status :: 3 - Alpha
Classifier: Intended Audience :: Developers
Classifier: License :: OSI Approved :: Apache Software License
Classifier: Natural Language :: English
Classifier: Programming Language :: Python
Classifier: Programming Language :: Python :: 3
Classifier: Programming Language :: Python :: 3.6
Classifier: Programming Language :: Python :: 3.7
Requires-Python: >=3.6
Requires-Dist: psutil
